pyInterDemand/__init__.py
pyInterDemand/algorithm/__init__.py
pyInterDemand/algorithm/intermittent.py
pyInterDemand-1.4.3.dist-info/LICENSE
pyInterDemand-1.4.3.dist-info/METADATA
pyInterDemand-1.4.3.dist-info/WHEEL
pyInterDemand-1.4.3.dist-info/top_level.txt
pyInterDemand-1.4.3.dist-info/RECORD
