Metadata-Version: 2.1
Name: pyInterDemand
Version: 1.4.3
Summary: pyInterDemand a Python Library for Intermittent Demand Methods
Home-page: https://github.com/Valdecy/pyInterDemand
Author: Valdecy Pereira
Author-email: valdecy.pereira@gmail.com
License: GNU
License-File: LICENSE
Requires-Dist: matplotlib
Requires-Dist: numpy
Requires-Dist: pandas
